setup.py
funniest/__init__.py
leo_funniest.egg-info/PKG-INFO
leo_funniest.egg-info/SOURCES.txt
leo_funniest.egg-info/dependency_links.txt
leo_funniest.egg-info/not-zip-safe
leo_funniest.egg-info/top_level.txt