Metadata-Version: 1.0
Name: leo-funniest
Version: 0.1
Summary: The funniest joke in the world
Home-page: http://github.com/jwplayer/discovery-integration-tests
Author: Flying Circus
Author-email: flyingcircus@example.com
License: MIT
Platform: UNKNOWN
